LICENSE
MANIFEST.in
README.md
setup.py
topsis_by_manmeet/__init__.py
topsis_by_manmeet/topsis_by_manmeet.py
topsis_by_manmeet.egg-info/PKG-INFO
topsis_by_manmeet.egg-info/SOURCES.txt
topsis_by_manmeet.egg-info/dependency_links.txt
topsis_by_manmeet.egg-info/requires.txt
topsis_by_manmeet.egg-info/top_level.txt