Metadata-Version: 1.1
Name: topsis-by-manmeet
Version: 0.1
Summary: Topsis
Home-page: https://github.com/manmeetkahlon/topsispython
Author: Manmeet Kaur
Author-email: manmeetkahlon2904@gmail.com
License: MIT
Keywords: SOME,MEANINGFULL,KEYWORDS
Platform: UNKNOWN
Classifier: Development Status :: 3 - Alpha
Classifier: Intended Audience :: Developers
Classifier: Topic :: Software Development :: Build Tools
Classifier: License :: OSI Approved :: MIT License
Classifier: Programming Language :: Python :: 3
Classifier: Programming Language :: Python :: 3.4
Classifier: Programming Language :: Python :: 3.5
Classifier: Programming Language :: Python :: 3.6
